{
  "BurgerMenu": [
    {
      "BurgerName": "DoubleCheeseBurger",
      "BurgerRecipe": [
        "lettuce 1",
        "cheese",
        "beef 1",
        "buns"
      ]
    },

    {
      "BurgerName": "CheeseBurger",
      "BurgerRecipe": [
        "lettuce 1",
        "cheese",
        "beef 1",
        "buns"
      ]
    },

    {
      "BurgerName": "ChickenBurger",
      "BurgerRecipe": [
        "lettuce 1",
        "chicken",
        "buns"
      ]
    },

    {
      "BurgerName": "TomatoChickenBurger",
      "BurgerRecipe":[
        "lettuce 1",
        "chicken",
        "tomato",
        "buns"
      ]
    },

    {
      "BurgerName": "Big Bag",
      "BurgerRecipe":[
        "lettuce 1",
        "beef",
        "bread",
        "beef",
        "tomato",
        "buns"
      ]
    }
  ]
}